better_terminal/Terminal.py
better_terminal/__init__.py
better_terminal-0.0.0.dist-info/LICENSE
better_terminal-0.0.0.dist-info/METADATA
better_terminal-0.0.0.dist-info/WHEEL
better_terminal-0.0.0.dist-info/top_level.txt
better_terminal-0.0.0.dist-info/RECORD
