Metadata-Version: 2.1
Name: better-terminal
Version: 0.0.0
Summary: A to create a better ui with your terminal.
Home-page: https://github.com/imperior-dev/better_terminal.git
Author: Pie
Author-email: owner@imperior.me
Classifier: Programming Language :: Python :: 3
Classifier: License :: OSI Approved :: MIT License
Classifier: Operating System :: OS Independent
Requires-Python: >=3.0
License-File: LICENSE
